hsadev/__init__.py
hsadev/logger.py
hsadev/request.py
hsadev/util.py
hsadev_kit-0.0.6.dist-info/LICENSE.txt
hsadev_kit-0.0.6.dist-info/METADATA
hsadev_kit-0.0.6.dist-info/WHEEL
hsadev_kit-0.0.6.dist-info/top_level.txt
hsadev_kit-0.0.6.dist-info/RECORD
