Metadata-Version: 2.1
Name: hsadev-kit
Version: 0.0.6
Summary: Package for personal
Home-page: http://dev.secuman.com/secuman/hsadev_kit
Author: secuman83
Author-email: secuman83@outlook.com
Project-URL: Bug Tracker, http://dev.secuman.com/secuman/hsadev_kit/-/issues
Classifier: Programming Language :: Python :: 3
Classifier: License :: OSI Approved :: MIT License
Classifier: Operating System :: OS Independent
Requires-Python: >=3.6
License-File: LICENSE.txt
Requires-Dist: requests
Requires-Dist: bs4
Requires-Dist: urllib3
